{
    "categories": [
        {
            "id": 1,
            "name": "Nintendo Switch"
        },
        {
            "id": 2,
            "name": "PlayStation 5"
        },
        {
            "id": 3,
            "name": "Xbox Series X"
        },
        {
            "id": 4,
            "name": "Multiplataforma (Genérico)"
        }
    ],
    "products": [
        {
            "id": 1001,
            "name": "Super Mario 3D World + Bowser's Fury (Físico)",
            "price": 59.99,
            "description": "Cartucho físico Switch. Incluye la expansión Bowser's Fury.",
            "stock": 35,
            "featured": true,
            "formato": "Físico",
            "image_url": "assets/img/mario_3d_physical.jpg",
            "id_categoria": 1
        },
        {
            "id": 1002,
            "name": "Super Mario 3D World + Bowser's Fury (Digital)",
            "price": 54.99,
            "description": "Código de descarga digital Switch.",
            "stock": 999,
            "featured": false,
            "formato": "Digital",
            "image_url": "assets/img/mario_3d_digital.jpg",
            "id_categoria": 1
        },
        {
            "id": 1003,
            "name": "Zelda Breath of the Wild (Físico)",
            "price": 64.99,
            "description": "Cartucho físico Switch. La aventura que redefinió Hyrule.",
            "stock": 25,
            "featured": true,
            "formato": "Físico",
            "image_url": "assets/img/zelda_botw_physical.jpg",
            "id_categoria": 1
        },
        {
            "id": 1004,
            "name": "Zelda Breath of the Wild (Digital)",
            "price": 59.99,
            "description": "Código de descarga digital Switch.",
            "stock": 999,
            "featured": false,
            "formato": "Digital",
            "image_url": "assets/img/zelda_botw_digital.jpg",
            "id_categoria": 1
        },
        {
            "id": 1005,
            "name": "Pokémon Escarlata (Físico)",
            "price": 49.99,
            "description": "Cartucho físico Switch. Viaja por la región de Paldea.",
            "stock": 40,
            "featured": false,
            "formato": "Físico",
            "image_url": "assets/img/pokemon_sc_physical.jpg",
            "id_categoria": 1
        },
        {
            "id": 1006,
            "name": "Pokémon Escarlata (Digital)",
            "price": 44.99,
            "description": "Código de descarga digital Switch.",
            "stock": 999,
            "featured": false,
            "formato": "Digital",
            "image_url": "assets/img/pokemon_sc_digital.jpg",
            "id_categoria": 1
        },
        {
            "id": 1007,
            "name": "Animal Crossing: New Horizons (Físico)",
            "price": 49.99,
            "description": "Cartucho físico Switch. Construye tu propia isla paradisíaca.",
            "stock": 30,
            "featured": true,
            "formato": "Físico",
            "image_url": "assets/img/acnh_physical.jpg",
            "id_categoria": 1
        },
        {
            "id": 1008,
            "name": "Animal Crossing: New Horizons (Digital)",
            "price": 44.99,
            "description": "Código de descarga digital Switch.",
            "stock": 999,
            "featured": false,
            "formato": "Digital",
            "image_url": "assets/img/acnh_digital.jpg",
            "id_categoria": 1
        },
        {
            "id": 1009,
            "name": "The Legend of Zelda Tears of the Kingdom (Físico)",
            "price": 69.99,
            "description": "Cartucho físico Switch. La gran secuela de BOTW.",
            "stock": 50,
            "featured": true,
            "formato": "Físico",
            "image_url": "assets/img/zelda_totk_physical.jpg",
            "id_categoria": 1
        },
        {
            "id": 1010,
            "name": "The Legend of Zelda Tears of the Kingdom (Digital)",
            "price": 64.99,
            "description": "Código de descarga digital Switch.",
            "stock": 999,
            "featured": false,
            "formato": "Digital",
            "image_url": "assets/img/zelda_totk_digital.jpg",
            "id_categoria": 1
        },
        {
            "id": 1011,
            "name": "Mario Odyssey (Físico)",
            "price": 59.99,
            "description": "Cartucho físico Switch. Una de las mejores aventuras 3D de Mario.",
            "stock": 25,
            "featured": true,
            "formato": "Físico",
            "image_url": "assets/img/mario_odyssey_physical.jpg",
            "id_categoria": 1
        },
        {
            "id": 1012,
            "name": "Mario Odyssey (Digital)",
            "price": 54.99,
            "description": "Código de descarga digital Switch.",
            "stock": 999,
            "featured": false,
            "formato": "Digital",
            "image_url": "assets/img/mario_odyssey_digital.jpg",
            "id_categoria": 1
        },
        {
            "id": 1013,
            "name": "Pokémon Mundo Misterioso Equipo de Rescate DX (Físico)",
            "price": 49.99,
            "description": "Cartucho físico Switch. Remake del clásico de GBA/NDS.",
            "stock": 20,
            "featured": false,
            "formato": "Físico",
            "image_url": "assets/img/pokemon_mystery_physical.jpg",
            "id_categoria": 1
        },
        {
            "id": 1014,
            "name": "Pokémon Mundo Misterioso Equipo de Rescate DX (Digital)",
            "price": 44.99,
            "description": "Código de descarga digital Switch.",
            "stock": 999,
            "featured": false,
            "formato": "Digital",
            "image_url": "assets/img/pokemon_mystery_digital.jpg",
            "id_categoria": 1
        },
        {
            "id": 1015,
            "name": "Marvel Spiderman (Físico)",
            "price": 39.99,
            "description": "Edición física PS5. Juega como Peter Parker en Nueva York.",
            "stock": 20,
            "featured": true,
            "formato": "Físico",
            "image_url": "assets/img/spiderman_physical.jpg",
            "id_categoria": 2
        },
        {
            "id": 1016,
            "name": "Marvel Spiderman (Digital)",
            "price": 34.99,
            "description": "Código de descarga digital PS5.",
            "stock": 999,
            "featured": false,
            "formato": "Digital",
            "image_url": "assets/img/spiderman_digital.jpg",
            "id_categoria": 2
        },
        {
            "id": 1017,
            "name": "Kingdom Hearts II.5 Remix (Físico)",
            "price": 19.99,
            "description": "Edición física PS5. Compilación que incluye KH2 Final Mix.",
            "stock": 25,
            "featured": false,
            "formato": "Físico",
            "image_url": "assets/img/kh25_physical.jpg",
            "id_categoria": 2
        },
        {
            "id": 1018,
            "name": "Kingdom Hearts II.5 Remix (Digital)",
            "price": 14.99,
            "description": "Código de descarga digital PS5.",
            "stock": 999,
            "featured": false,
            "formato": "Digital",
            "image_url": "assets/img/kh25_digital.jpg",
            "id_categoria": 2
        },
        {
            "id": 1019,
            "name": "Astro's Playroom (Físico)",
            "price": 19.90,
            "description": "Disco físico PS5. Un showcase del DualSense.",
            "stock": 10,
            "featured": false,
            "formato": "Físico",
            "image_url": "assets/img/astro_physical.jpg",
            "id_categoria": 2
        },
        {
            "id": 1020,
            "name": "Astro's Playroom (Digital)",
            "price": 14.90,
            "description": "Código de descarga digital PS5.",
            "stock": 999,
            "featured": false,
            "formato": "Digital",
            "image_url": "assets/img/astro_digital.jpg",
            "id_categoria": 2
        },
        {
            "id": 1021,
            "name": "Persona 5 Royale (Físico)",
            "price": 39.99,
            "description": "Edición física PS5. La edición definitiva del JRPG.",
            "stock": 20,
            "featured": true,
            "formato": "Físico",
            "image_url": "assets/img/p5r_physical.jpg",
            "id_categoria": 2
        },
        {
            "id": 1022,
            "name": "Persona 5 Royale (Digital)",
            "price": 34.99,
            "description": "Código de descarga digital PS5.",
            "stock": 999,
            "featured": false,
            "formato": "Digital",
            "image_url": "assets/img/p5r_digital.jpg",
            "id_categoria": 2
        },
        {
            "id": 1023,
            "name": "Astro Bot (Físico)",
            "price": 59.99,
            "description": "Disco físico PS5. El gran juego de plataformas exclusivo.",
            "stock": 15,
            "featured": true,
            "formato": "Físico",
            "image_url": "assets/img/astro_bot_physical.jpg",
            "id_categoria": 2
        },
        {
            "id": 1024,
            "name": "Astro Bot (Digital)",
            "price": 54.99,
            "description": "Código de descarga digital PS5.",
            "stock": 999,
            "featured": false,
            "formato": "Digital",
            "image_url": "assets/img/astro_bot_digital.jpg",
            "id_categoria": 2
        },
        {
            "id": 1025,
            "name": "Kingdom Hearts III (Físico)",
            "price": 29.99,
            "description": "Edición física PS5. La conclusión de la saga.",
            "stock": 20,
            "featured": false,
            "formato": "Físico",
            "image_url": "assets/img/kh3_physical.jpg",
            "id_categoria": 2
        },
        {
            "id": 1026,
            "name": "Kingdom Hearts III (Digital)",
            "price": 24.99,
            "description": "Código de descarga digital PS5.",
            "stock": 999,
            "featured": false,
            "formato": "Digital",
            "image_url": "assets/img/kh3_digital.jpg",
            "id_categoria": 2
        },
        {
            "id": 1027,
            "name": "Marvel Spiderman Miles Morales (Físico)",
            "price": 49.99,
            "description": "Edición física PS5. Expansión independiente con Miles Morales.",
            "stock": 20,
            "featured": true,
            "formato": "Físico",
            "image_url": "assets/img/miles_morales_physical.jpg",
            "id_categoria": 2
        },
        {
            "id": 1028,
            "name": "Marvel Spiderman Miles Morales (Digital)",
            "price": 44.99,
            "description": "Código de descarga digital PS5.",
            "stock": 999,
            "featured": false,
            "formato": "Digital",
            "image_url": "assets/img/miles_morales_digital.jpg",
            "id_categoria": 2
        },
        {
            "id": 1029,
            "name": "Persona 5 Strikers (Físico)",
            "price": 29.99,
            "description": "Edición física PS5. Secuela de acción de Persona 5.",
            "stock": 15,
            "featured": false,
            "formato": "Físico",
            "image_url": "assets/img/p5s_physical.jpg",
            "id_categoria": 2
        },
        {
            "id": 1030,
            "name": "Persona 5 Strikers (Digital)",
            "price": 24.99,
            "description": "Código de descarga digital PS5.",
            "stock": 999,
            "featured": false,
            "formato": "Digital",
            "image_url": "assets/img/p5s_digital.jpg",
            "id_categoria": 2
        },
        {
            "id": 1031,
            "name": "Dragon Ball Sparking Zero (Físico)",
            "price": 69.99,
            "description": "Edición física Xbox Series X. El esperado nuevo Budokai Tenkaichi.",
            "stock": 40,
            "featured": false,
            "formato": "Físico",
            "image_url": "assets/img/dbz_sparking_physical.jpg",
            "id_categoria": 3
        },
        {
            "id": 1032,
            "name": "Dragon Ball Sparking Zero (Digital)",
            "price": 64.99,
            "description": "Código de descarga digital Xbox Series X.",
            "stock": 999,
            "featured": false,
            "formato": "Digital",
            "image_url": "assets/img/dbz_sparking_digital.jpg",
            "id_categoria": 3
        },
        {
            "id": 1033,
            "name": "Mafia III Definitive Edition (Físico)",
            "price": 19.99,
            "description": "Edición física Xbox Series X. Trilogía con todos los DLC.",
            "stock": 30,
            "featured": false,
            "formato": "Físico",
            "image_url": "assets/img/mafia3_physical.jpg",
            "id_categoria": 3
        },
        {
            "id": 1034,
            "name": "Mafia III Definitive Edition (Digital)",
            "price": 14.99,
            "description": "Código de descarga digital Xbox Series X.",
            "stock": 999,
            "featured": false,
            "formato": "Digital",
            "image_url": "assets/img/mafia3_digital.jpg",
            "id_categoria": 3
        },
        {
            "id": 1035,
            "name": "Call of Duty Advanced Warfare (Físico)",
            "price": 10.00,
            "description": "Edición física Xbox One/Series X (Usada). Shooter futurista.",
            "stock": 10,
            "featured": false,
            "formato": "Físico",
            "image_url": "assets/img/cod_aw_physical.jpg",
            "id_categoria": 3
        },
        {
            "id": 1036,
            "name": "Call of Duty Advanced Warfare (Digital)",
            "price": 15.00,
            "description": "Código de descarga digital Xbox One/Series X.",
            "stock": 999,
            "featured": false,
            "formato": "Digital",
            "image_url": "assets/img/cod_aw_digital.jpg",
            "id_categoria": 3
        },
        {
            "id": 1037,
            "name": "Injustice 2 (Físico)",
            "price": 14.99,
            "description": "Edición física Xbox Series X. Lucha de superhéroes de DC.",
            "stock": 25,
            "featured": false,
            "formato": "Físico",
            "image_url": "assets/img/injustice2_physical.jpg",
            "id_categoria": 3
        },
        {
            "id": 1038,
            "name": "Injustice 2 (Digital)",
            "price": 9.99,
            "description": "Código de descarga digital Xbox Series X.",
            "stock": 999,
            "featured": false,
            "formato": "Digital",
            "image_url": "assets/img/injustice2_digital.jpg",
            "id_categoria": 3
        },
        {
            "id": 1039,
            "name": "Red Dead Redemption II (Físico)",
            "price": 24.99,
            "description": "Edición física Xbox Series X. El épico western de Rockstar.",
            "stock": 30,
            "featured": true,
            "formato": "Físico",
            "image_url": "assets/img/rdr2_physical.jpg",
            "id_categoria": 3
        },
        {
            "id": 1040,
            "name": "Red Dead Redemption II (Digital)",
            "price": 19.99,
            "description": "Código de descarga digital Xbox Series X.",
            "stock": 999,
            "featured": false,
            "formato": "Digital",
            "image_url": "assets/img/rdr2_digital.jpg",
            "id_categoria": 3
        },
        {
            "id": 1041,
            "name": "Bioshock I (Físico)",
            "price": 14.99,
            "description": "Edición física Multiplataforma. Remasterizado del clásico de Rapture.",
            "stock": 50,
            "featured": true,
            "formato": "Físico",
            "image_url": "assets/img/bioshock_physical.jpg",
            "id_categoria": 4
        },
        {
            "id": 1042,
            "name": "Bioshock I (Digital)",
            "price": 9.99,
            "description": "Código de descarga digital Multiplataforma.",
            "stock": 999,
            "featured": false,
            "formato": "Digital",
            "image_url": "assets/img/bioshock_digital.jpg",
            "id_categoria": 4
        },
        {
            "id": 1043,
            "name": "Blasphemous (Físico)",
            "price": 29.99,
            "description": "Edición física Multiplataforma. Metroidvania español 'soulslike'.",
            "stock": 15,
            "featured": true,
            "formato": "Físico",
            "image_url": "assets/img/blasphemous_physical.jpg",
            "id_categoria": 4
        },
        {
            "id": 1044,
            "name": "Blasphemous (Digital)",
            "price": 19.99,
            "description": "Código de descarga digital Multiplataforma.",
            "stock": 999,
            "featured": false,
            "formato": "Digital",
            "image_url": "assets/img/blasphemous_digital.jpg",
            "id_categoria": 4
        },
        {
            "id": 1045,
            "name": "Sonic Forces (Físico)",
            "price": 9.99,
            "description": "Edición física Multiplataforma. Plataformas de alta velocidad.",
            "stock": 20,
            "featured": false,
            "formato": "Físico",
            "image_url": "assets/img/sonic_forces_physical.jpg",
            "id_categoria": 4
        },
        {
            "id": 1046,
            "name": "Sonic Forces (Digital)",
            "price": 7.99,
            "description": "Código de descarga digital Multiplataforma.",
            "stock": 999,
            "featured": false,
            "formato": "Digital",
            "image_url": "assets/img/sonic_forces_digital.jpg",
            "id_categoria": 4
        },
        {
            "id": 1047,
            "name": "Dragon Ball Z: Kakarot (Físico)",
            "price": 35.00,
            "description": "Edición física Multiplataforma. Revive la historia de Goku.",
            "stock": 45,
            "featured": true,
            "formato": "Físico",
            "image_url": "assets/img/kakarot_physical.jpg",
            "id_categoria": 4
        },
        {
            "id": 1048,
            "name": "Dragon Ball Z: Kakarot (Digital)",
            "price": 30.00,
            "description": "Código de descarga digital Multiplataforma.",
            "stock": 999,
            "featured": false,
            "formato": "Digital",
            "image_url": "assets/img/kakarot_digital.jpg",
            "id_categoria": 4
        },
        {
            "id": 1049,
            "name": "It Takes Two (Físico)",
            "price": 19.99,
            "description": "Edición física Multiplataforma. Aventura cooperativa premiada.",
            "stock": 30,
            "featured": false,
            "formato": "Físico",
            "image_url": "assets/img/itt_physical.jpg",
            "id_categoria": 4
        },
        {
            "id": 1050,
            "name": "It Takes Two (Digital)",
            "price": 14.99,
            "description": "Código de descarga digital Multiplataforma.",
            "stock": 999,
            "featured": false,
            "formato": "Digital",
            "image_url": "assets/img/itt_digital.jpg",
            "id_categoria": 4
        },
        {
            "id": 1051,
            "name": "Blasphemous II (Físico)",
            "price": 39.99,
            "description": "Edición física Multiplataforma. La secuela del soulslike español.",
            "stock": 10,
            "featured": false,
            "formato": "Físico",
            "image_url": "assets/img/blasphemous2_physical.jpg",
            "id_categoria": 4
        },
        {
            "id": 1052,
            "name": "Blasphemous II (Digital)",
            "price": 29.99,
            "description": "Código de descarga digital Multiplataforma.",
            "stock": 999,
            "featured": false,
            "formato": "Digital",
            "image_url": "assets/img/blasphemous2_digital.jpg",
            "id_categoria": 4
        },
        {
            "id": 1053,
            "name": "Dark Souls Remastered (Físico)",
            "price": 29.99,
            "description": "Edición física Multiplataforma. El clásico 'soulslike' original.",
            "stock": 30,
            "featured": true,
            "formato": "Físico",
            "image_url": "assets/img/ds_remastered_physical.jpg",
            "id_categoria": 4
        },
        {
            "id": 1054,
            "name": "Dark Souls Remastered (Digital)",
            "price": 25.00,
            "description": "Código de descarga digital Multiplataforma.",
            "stock": 999,
            "featured": false,
            "formato": "Digital",
            "image_url": "assets/img/ds_remastered_digital.jpg",
            "id_categoria": 4
        },
        {
            "id": 1055,
            "name": "Balatro (Físico)",
            "price": 29.99,
            "description": "Edición física Multiplataforma. Roguelike de póker adictivo.",
            "stock": 10,
            "featured": false,
            "formato": "Físico",
            "image_url": "assets/img/balatro_physical.jpg",
            "id_categoria": 4
        },
        {
            "id": 1056,
            "name": "Balatro (Digital)",
            "price": 19.99,
            "description": "Código de descarga digital Multiplataforma.",
            "stock": 999,
            "featured": false,
            "formato": "Digital",
            "image_url": "assets/img/balatro_digital.jpg",
            "id_categoria": 4
        },
        {
            "id": 1057,
            "name": "Batman Arkham Knight (Físico)",
            "price": 14.99,
            "description": "Edición física Multiplataforma. Cierre de la saga Arkham.",
            "stock": 30,
            "featured": false,
            "formato": "Físico",
            "image_url": "assets/img/batman_ak_physical.jpg",
            "id_categoria": 4
        },
        {
            "id": 1058,
            "name": "Batman Arkham Knight (Digital)",
            "price": 9.99,
            "description": "Código de descarga digital Multiplataforma.",
            "stock": 999,
            "featured": false,
            "formato": "Digital",
            "image_url": "assets/img/batman_ak_digital.jpg",
            "id_categoria": 4
        },
        {
            "id": 1059,
            "name": "Stardew Valley (Físico)",
            "price": 19.99,
            "description": "Edición física Multiplataforma. El clásico de granjas y simulación.",
            "stock": 25,
            "featured": false,
            "formato": "Físico",
            "image_url": "assets/img/stardew_physical.jpg",
            "id_categoria": 4
        },
        {
            "id": 1060,
            "name": "Stardew Valley (Digital)",
            "price": 9.99,
            "description": "Código de descarga digital Multiplataforma.",
            "stock": 999,
            "featured": false,
            "formato": "Digital",
            "image_url": "assets/img/stardew_digital.jpg",
            "id_categoria": 4
        },
        {
            "id": 1061,
            "name": "Tekken 7 (Físico)",
            "price": 19.99,
            "description": "Edición física Multiplataforma. Juego de lucha de Bandai Namco.",
            "stock": 30,
            "featured": false,
            "formato": "Físico",
            "image_url": "assets/img/tekken7_physical.jpg",
            "id_categoria": 4
        },
        {
            "id": 1062,
            "name": "Tekken 7 (Digital)",
            "price": 14.99,
            "description": "Código de descarga digital Multiplataforma.",
            "stock": 999,
            "featured": false,
            "formato": "Digital",
            "image_url": "assets/img/tekken7_digital.jpg",
            "id_categoria": 4
        },
        {
            "id": 1063,
            "name": "Hollow Knight (Físico)",
            "price": 39.99,
            "description": "Edición física coleccionista Multiplataforma. Metroidvania aclamado.",
            "stock": 15,
            "featured": true,
            "formato": "Físico",
            "image_url": "assets/img/hollow_knight_physical.jpg",
            "id_categoria": 4
        },
        {
            "id": 1064,
            "name": "Hollow Knight (Digital)",
            "price": 14.99,
            "description": "Código de descarga digital Multiplataforma.",
            "stock": 999,
            "featured": false,
            "formato": "Digital",
            "image_url": "assets/img/hollow_knight_digital.jpg",
            "id_categoria": 4
        },
        {
            "id": 1065,
            "name": "One Piece Odyssey (Físico)",
            "price": 39.99,
            "description": "Edición física Multiplataforma. RPG basado en el anime.",
            "stock": 25,
            "featured": false,
            "formato": "Físico",
            "image_url": "assets/img/one_piece_od_physical.jpg",
            "id_categoria": 4
        },
        {
            "id": 1066,
            "name": "One Piece Odyssey (Digital)",
            "price": 34.99,
            "description": "Código de descarga digital Multiplataforma.",
            "stock": 999,
            "featured": false,
            "formato": "Digital",
            "image_url": "assets/img/one_piece_od_digital.jpg",
            "id_categoria": 4
        }
    ]
}